{
    "m_Version": 7,
    "TraderName": "Weapons",
    "DisplayName": "#STR_EXPANSION_MARKET_TRADER_WEAPONS",
    "TraderIcon": "Shotgun",
    "Currencies": [
        "money_ruble5000",
        "money_ruble2000",
        "money_ruble1000",
        "money_ruble500",
        "money_ruble200",
        "money_ruble100",
        "money_ruble50",
        "money_ruble10",
        "money_ruble5",
        "money_ruble2",
        "money_ruble1"
    ],
    "Categories": [],
    "Items": {
        "brassknuckles_shiny": 1,
        "brassknuckles_dull": 1,
        "mag_cmag_10rnd": 3,
        "acogoptic": 3,
        "acogoptic_6x": 3,
        "kukriknife": 1,
        "mag_saiga_8rnd": 3,
        "ammobox_expansion_338_15rnd": 1,
        "ammobox_545x39tracer_20rnd": 1,
        "expansion_ammobox_8mm_15rnd": 1,
        "ammobox_762x39tracer_20rnd": 1,
        "vss": 1,
        "ammo_45acp": 1,
        "mp5k": 1,
        "izh43shotgun": 1,
        "famas": 1,
        "mp5_plastichndgrd": 3,
        "stunbaton": 1,
        "ammo_762x54tracer": 1,
        "ammobox_00buck_10rnd": 1,
        "mag_ruger1022_30rnd": 3,
        "puscopeoptic": 3,
        "ammobox_556x45tracer_20rnd": 1,
        "ammo_308win": 1,
        "m4_carryhandleoptic": 3,
        "expansion_kedr": 1,
        "pso11optic": 3,
        "engraved1911": 1,
        "ak_plastichndgrd": 3,
        "mag_expansion_m14_20rnd": 3,
        "m4_cqbbttstck": 3,
        "ammo_expansion_46x30": 1,
        "fal_foldingbttstck": 3,
        "mag_expansion_vityaz_30rnd": 3,
        "buisoptic": 3,
        "ammo_556x45tracer": 1,
        "ammo_308wintracer": 1,
        "ammo_556x45": 1,
        "ammo_357": 1,
        "pipe": 1,
        "mp5k_stockbttstck": 3,
        "mag_mp5_15rnd": 3,
        "flaregun": 1,
        "broom_birch": 1,
        "ghillieatt_woodland": 3,
        "fal_oebttstck": 3,
        "expansion_pmii25optic": 3,
        "mag_deagle_9rnd": 3,
        "ammo_9x19": 1,
        "ammobox_9x19_25rnd": 1,
        "huntingoptic": 3,
        "expansionexps3holooptic": 3,
        "ammo_flarered": 1,
        "m4_mphndgrd": 3,
        "expansion_benellim4": 1,
        "svd": 1,
        "expansion_m14": 1,
        "expansion_m16": 1,
        "mag_saiga_5rnd": 3,
        "mp5_railhndgrd": 3,
        "combatknife": 1,
        "expansion_ammo_arrowbolt": 1,
        "b95": 1,
        "baseballbat": 1,
        "pistoloptic": 3,
        "machete": 1,
        "ammobox_expansion_46x30_25rnd": 1,
        "kitchenknife": 1,
        "ak_foldingbttstck": 3,
        "m68optic": 3,
        "expansion_awm": 1,
        "expansion_m1a": 1,
        "ammo_545x39tracer": 1,
        "ammo_12gapellets": 1,
        "ak74_woodbttstck": 3,
        "expansion_kar98_bayonet": 3,
        "expansion_g36": 1,
        "mag_expansion_mpx_50rnd": 3,
        "mag_stanag_60rnd": 3,
        "ammo_9x39": 1,
        "mag_expansion_mp7_40rnd": 3,
        "mag_expansion_m9_15rnd": 3,
        "mag_expansion_kedr_20rnd": 3,
        "orientalmachete": 1,
        "fnp45_mrdsoptic": 3,
        "ammo_380": 1,
        "ak_suppressor": 3,
        "broom": 1,
        "aks74u_bttstck": 3,
        "mag_expansion_g36_30rnd": 3,
        "mag_vss_10rnd": 3,
        "ruger1022": 1,
        "mosin_bayonet": 3,
        "ammobox_12gaslug_10rnd": 1,
        "ghillieatt_mossy": 3,
        "ammobox_9x39ap_20rnd": 1,
        "mag_cz61_20rnd": 3,
        "m4_rishndgrd": 3,
        "mag_ruger1022_15rnd": 3,
        "mag_cmag_40rnd": 3,
        "ak_woodbttstck": 3,
        "cz61": 1,
        "mkii": 1,
        "ammo_expansion_338": 1,
        "kashtanoptic": 3,
        "m16a2": 1,
        "mag_mp5_30rnd": 3,
        "mag_ak74_30rnd": 3,
        "mag_cz527_5rnd": 3,
        "m4a1": 1,
        "ammo_9x39ap": 1,
        "mag_cmag_20rnd": 3,
        "m4_mpbttstck": 3,
        "m4_plastichndgrd": 3,
        "cz75": 1,
        "expansion_m1a_railatt": 3,
        "ak_plasticbttstck": 3,
        "asval": 1,
        "fangeknife": 1,
        "mag_akm_30rnd": 3,
        "mag_stanagcoupled_30rnd": 3,
        "ak74": 1,
        "ammo_flaregreen": 1,
        "ammobox_762x39_20rnd": 1,
        "mag_expansion_taser": 3,
        "expansionreflexmrsoptic": 3,
        "nailedbaseballbat": 1,
        "mag_akm_drum75rnd": 3,
        "mag_mkii_10rnd": 3,
        "ammobox_357_20rnd": 1,
        "mag_ak74_45rnd": 3,
        "ammobox_9x39_20rnd": 1,
        "glock19": 1,
        "expansion_kar98": 1,
        "reflexoptic": 3,
        "ammobox_12garubberslug_10rnd": 1,
        "makarovij70": 1,
        "mag_fal_20rnd": 3,
        "m4_suppressor": 3,
        "mag_glock_15rnd": 3,
        "fnx45": 1,
        "ammobox_380_35rnd": 1,
        "ammobox_762x54_20rnd": 1,
        "mag_val_20rnd": 3,
        "mag_expansion_m14_10rnd": 3,
        "expansionkar98scopeoptic": 3,
        "crudemachete": 1,
        "winchester70": 1,
        "ammo_762x39": 1,
        "ammobox_308wintracer_20rnd": 1,
        "mag_scout_5rnd": 3,
        "mag_famas_25rnd": 3,
        "steakknife": 1,
        "cattleprod": 1,
        "mag_cz75_15rnd": 3,
        "ammo_545x39": 1,
        "mosin_compensator": 3,
        "cz527": 1,
        "mp133shotgun": 1,
        "mag_saiga_drum20rnd": 3,
        "ammobox_556x45_20rnd": 1,
        "kobraoptic": 3,
        "ammobox_308win_20rnd": 1,
        "mag_1911_7rnd": 3,
        "ammobox_22_50rnd": 1,
        "mosin9130": 1,
        "expansion_mpx": 1,
        "ak_woodhndgrd": 3,
        "repeater": 1,
        "kazuaroptic": 3,
        "starlightoptic": 3,
        "mag_ump_25rnd": 3,
        "ghillieatt_tan": 3,
        "ammo_12gaslug": 1,
        "magnum": 1,
        "mag_svd_10rnd": 3,
        "akm": 1,
        "expansion_mp5": 1,
        "expansion_mp7": 1,
        "expansion_crossbow": 1,
        "mag_fnx45_15rnd": 3,
        "ammo_762x54": 1,
        "ak_railhndgrd": 3,
        "izh18": 1,
        "m9a1_bayonet": 3,
        "colt1911": 1,
        "expansion_vityazsn": 1,
        "huntingknife": 1,
        "mag_akm_palm30rnd": 3,
        "scout": 1,
        "mag_expansion_awm_5rnd": 3,
        "ammo_12garubberslug": 1,
        "ump45": 1,
        "m4_t3nrdsoptic": 3,
        "mag_ak101_30rnd": 3,
        "ammo_22": 1,
        "ammobox_545x39_20rnd": 1,
        "expansion_dt11": 1,
        "saiga": 1,
        "ammo_flare": 1,
        "ammo_flareblue": 1,
        "aks74u": 1,
        "ammobox_45acp_25rnd": 1,
        "saiga_bttstck": 3,
        "deagle": 1,
        "mag_stanag_30rnd": 3,
        "ak74_hndgrd": 3,
        "ak101": 1,
        "expansiondeltapointoptic": 3,
        "sks_bayonet": 3,
        "mag_ij70_8rnd": 3,
        "mp5_compensator": 3,
        "pistolsuppressor": 3,
        "mag_cmag_30rnd": 3,
        "fal": 1,
        "expansionhamroptic": 3,
        "pso1optic": 3,
        "expansion_m9": 1,
        "expansion_ammo_8mm": 1,
        "ak_bayonet": 3,
        "m4_oebttstck": 3,
        "ammobox_762x54tracer_20rnd": 1,
        "expansion_longhorn": 1,
        "ammo_762x39tracer": 1,
        "deagle_gold": 1,
        "TTC_KAC": 1,
        "TTC_MAS36": 1,
        "TTC_Winchester1873": 1,
        "TTC_kar98k": 1,
        "TTC_R700": 1,
        "TTCSR25": 1,
        "TTCSR25_Desert": 1,
        "TTCSR25_Snow": 1,
        "TTCSR25_OD": 1,
        "TTC_HK416Tan": 1,
        "TTC_HK416OD": 1,
        "TTC_HK416Black": 1,
        "TTC_SG552": 1,
        "TTC_SG552_Wood": 1,
        "TTC_SG552_Black": 1,
        "TTC_SG550": 1,
        "TTC_SG550_Black": 1,
        "TTC_SG550_Pink": 1,
        "TTC_M16": 1,
        "TTC_AEK973": 1,
        "TTC_M4DMR": 1,
        "TTC_M4DMROD": 1,
        "TTC_M4DMRDesert": 1,
        "TTC_FD338": 1,
        "TTC_AACHoney": 1,
        "TTC_AACHoney_B": 1,
        "TTC_AACHoney_300blk": 1,
        "TTC_AACHoney_300blk_B": 1,
        "TTC_M24": 1,
        "TTC_M24_Bjorn": 1,
        "TTC_M24_Woodland": 1,
        "TTC_M24_WoodlandOld": 1,
        "TTC_SCARHBlack": 1,
        "TTC_SCARL": 1,
        "TTC_SCARLSnow": 1,
        "TTC_SCARLBlack": 1,
        "TTC_M16A4": 1,
        "TTC_Beowulf": 1,
        "TTC_M82": 1,
        "TTC_M82_Tan": 1,
        "TTC_HKG28": 1,
        "TTC_LeeEnfield": 1,
        "TTC_M1Garand": 1,
        "TTC_M4Tac": 1,
        "TTC_M14": 1,
        "TTC_MRAD": 1,
        "TTC_XM2010": 1,
        "TTC_AK12": 1,
        "TTC_AK12_Worn": 1,
        "TTC_G3": 1,
        "TTC_Kimber": 1,
        "TTC_Mossberg": 1,
        "TTC_HK417": 1,
        "TTC_M9": 1,
        "TTC_AKMod": 1,
        "TTC_AKModPK": 1,
        "TTC_M110": 1,
        "TTC_Maverick": 1,
        "TTC_AG3": 1,
        "TTC_FAL": 1,
        "TTC_Raptr": 1,
        "TTC_M24_NEW_Wood": 1,
        "TTC_AVS36": 1,
        "TTC_CAR15": 1,
        "TTC_M1903": 1,
        "TTC_MCX": 1,
        "TTC_AKM": 1,
        "TTC_Deagle": 1,
        "TTC_Glock17": 1,
        "TTC_M9_Custom": 1,
        "TTC_MP5SD": 1,
        "TTC_MPX": 1,
        "TTC_PP91": 1,
        "TTC_UZI": 1,
        "TTC_MP7A1": 1,
        "TTC_SVT40": 1,
        "TTC_M4DMRSNOW": 1,
        "TTC_STG44": 1,
        "TTC_BAR": 1,
        "TTC_DMR_Barrel_556": 3,
        "TTC_DMR_Barrel_762": 3,
        "TTC_DMR_RifleFrame": 3,
        "TTC_AKMod_Barrel_76239": 3,
        "TTC_AKMod_Barrel_76254": 3,
        "TTC_AKMod_RifleFrame": 3,
        "TTC_Buttstock": 3,
        "TTC_Buttstock2": 3,
        "TTC_Buttstock3": 3,
        "TTC_Buttstock_Honey": 3,
        "TTC_Buttstock_Camo": 3,
        "TTC_Buttstock_Digitan": 3,
        "TTC_Buttstock_Tan": 3,
        "TTC_Buttstock_UPC": 3,
        "TTC_ButtstockHK": 3,
        "TTC_Buttstock_Morty": 3,
        "TTC_Buttstock_AK12": 3,
        "TTC_AKMod_bttstk": 3,
        "TTC_AKMod_Gold_bttstk": 3,
        "TTC_AKMod_Snow_bttstk": 3,
        "TTC_AKMod_Multi_bttstk": 3,
        "TTC_AKMod_Digi_bttstk": 3,
        "TTC_AKMod_Tan_bttstk": 3,
        "TTC_FAL_Wood_Bttstck": 3,
        "TTC_MPXMCX1_Bttstck": 3,
        "TTC_MPXMCX1_Bttstck2": 3,
        "TTC_MPXMCX2_Bttstck": 3,
        "TTC_Buttstock_CAR15": 3,
        "TTC_ButtstockHK_Black": 3,
        "TTC_M24New_mag_5rnd": 3,
        "Mag_SG_30Rnd": 3,
        "TTC_308Stanag": 3,
        "TTC_300Stanag": 3,
        "TTC_300Cmag": 3,
        "TTC_338mag_10rnd": 3,
        "TTC_M24mag_5rnd": 3,
        "TTC_SCARHMag": 3,
        "TTC_50Beo_mag": 3,
        "TTC_DMR_556Stanag_30rnd": 3,
        "TTC_DMR_556Stanag_30rnd_camo": 3,
        "TTC_DMR_556Stanag_30rnd_Digitan": 3,
        "TTC_DMR_556Stanag_30rnd_Tan": 3,
        "TTC_DMR_556Stanag_30rnd_UPC": 3,
        "TTC_DMR_556Stanag_100rnd": 3,
        "TTC_DMR_556Stanag_100rnd_camo": 3,
        "TTC_DMR_556Stanag_100rnd_Digitan": 3,
        "TTC_DMR_556Stanag_100rnd_Tan": 3,
        "TTC_DMR_556Stanag_100rnd_UPC": 3,
        "TTC_DMR_556Pmag_30rnd": 3,
        "TTC_DMR_556Pmag_30rnd_camo": 3,
        "TTC_DMR_556Pmag_30rnd_Digitan": 3,
        "TTC_DMR_556Pmag_30rnd_Tan": 3,
        "TTC_DMR_556Pmag_30rnd_UPC": 3,
        "TTC_DMR_556Pmag_40rnd": 3,
        "TTC_DMR_556Pmag_40rnd_camo": 3,
        "TTC_DMR_556Pmag_40rnd_Digitan": 3,
        "TTC_DMR_556Pmag_40rnd_Tan": 3,
        "TTC_DMR_556Pmag_40rnd_UPC": 3,
        "TTC_DMR_556Pmag_100rnd": 3,
        "TTC_DMR_556Pmag_100rnd_camo": 3,
        "TTC_DMR_556Pmag_100rnd_Digitan": 3,
        "TTC_DMR_556Pmag_100rnd_Tan": 3,
        "TTC_DMR_556Pmag_100rnd_UPC": 3,
        "TTC_DMR_762Stanag_20rnd": 3,
        "TTC_DMR_762Stanag_20rnd_camo": 3,
        "TTC_DMR_762Stanag_20rnd_Digitan": 3,
        "TTC_DMR_762Stanag_20rnd_Tan": 3,
        "TTC_DMR_762Stanag_20rnd_UPC": 3,
        "TTC_DMR_762Stanag_10rnd": 3,
        "TTC_DMR_762Stanag_10rnd_camo": 3,
        "TTC_DMR_762Stanag_10rnd_Digitan": 3,
        "TTC_DMR_762Stanag_10rnd_Tan": 3,
        "TTC_DMR_762Stanag_10rnd_UPC": 3,
        "TTC_M82_5rnd_Mag": 3,
        "TTC_M14_Mag_20rnd": 3,
        "TTC_338mag_5rnd": 3,
        "TTC_XM2010_10rnd": 3,
        "TTC_AK12_Drum_90rnd": 3,
        "TTC_G3_Magazine_20rnd": 3,
        "TTC_HK417_Magazine_20rnd": 3,
        "Mag_Kimber1911_10Rnd": 3,
        "TTC_Mag_M9_15Rnd": 3,
        "TTC_AKMod_762x54_30rnd": 3,
        "TTC_AKMod_762x54_65rnd": 3,
        "TTC_FAL_Magazine": 3,
        "TTC_Coupled_FAL_Magazine": 3,
        "TTC_AG3_Coupled_Magazine_40rnd": 3,
        "TTC_Raptr_Drum_45rnd": 3,
        "TTC_AVS36_Mag_10rnd": 3,
        "TTC_Deagle_Magazine_7rnd": 3,
        "TTC_Mag_Glock_17Rnd": 3,
        "TTC_Mag_M9_Custom_20Rnd": 3,
        "TTC_MPX_Mag_60rnd": 3,
        "TTC_MPX_Mag_30rnd": 3,
        "TTC_PP91_Mag_20rnd": 3,
        "TTC_UZI_Mag_30rnd": 3,
        "TTC_300Cmag_60rnd": 3,
        "TTC_MP7A1_Mag_40rnd": 3,
        "TTC_Mag_SVT40_10rnd": 3,
        "TTC_STG44_Magazine_30rnd": 3,
        "TTC_BAR_Magazine_20rnd": 3,
        "TTC_Universal_Suppressor_BLACK": 3,
        "TTC_Universal_Suppressor_CAMO": 3,
        "TTC_Honey_Suppressor": 3,
        "TTC_Universal_Suppressor_Tan": 3,
        "TTC_Universal_Suppressor_Snow": 3,
        "TTC_DMR_Suppressor": 3,
        "TTC_DMR_AFG": 3,
        "TTC_DMR_AFG_Green": 3,
        "TTC_DMR_AFG_Tan": 3,
        "TTC_DMR_VFG": 3,
        "TTC_DMR_VFG_Green": 3,
        "TTC_DMR_VFG_Tan": 3,
        "TTC_DMR_Bipod": 3,
        "TTC_M14Suppressor": 3,
        "TTC_AKMOD_AFG": 3,
        "TTC_AKMod_Suppressor": 3,
        "TTC_PistolSuppressor": 3,
        "TTC_DMR_Hndguard": 3,
        "TTC_DMR_HndguardOD": 3,
        "TTC_DMR_HndguardDesert": 3,
        "TTC_AKMod_Hndguard": 3,
        "TTC_AKMod_Gold_Hndguard": 3,
        "TTC_AKMod_Snow_Hndguard": 3,
        "TTC_AKMod_Multi_Hndguard": 3,
        "TTC_AKMod_Digi_Hndguard": 3,
        "TTC_AKMod_Tan_Hndguard": 3,
        "TTC_FAL_RIS_Hndgrd": 3,
        "TTC_FAL_Wood_Hndgrd": 3,
        "TTC_FAL_Poly_Hndgrd": 3,
        "TTC_Pistol_Light": 3,
        "TTC_SVT40_Bayonet": 3,
        "TTC_DMR_HndguardSnow": 3,
        "TTC_G3_Optic": 3,
        "TTC_BugBuster": 3,
        "TTC_Holo": 3,
        "TTC_HAMR": 3,
        "TTC_Razor": 3,
        "TTC_G28_Optic": 3,
        "TTC_G28_Optic_Black": 3,
        "TTC_Aimpoint2000": 3
    }
}